gfatpy/__init__.py
gfatpy/config.py
gfatpy/aeronet/__init__.py
gfatpy/aeronet/aeronet4lidar.py
gfatpy/aeronet/info.yml
gfatpy/aeronet/plot.py
gfatpy/aeronet/reader.py
gfatpy/aeronet/typing.py
gfatpy/aeronet/utils.py
gfatpy/assets/LOGO_GFAT_150pp
gfatpy/atmo/__init__.py
gfatpy/atmo/atmo.py
gfatpy/atmo/ecmwf.py
gfatpy/atmo/freudenthaler_molecular_properties.py
gfatpy/atmo/rayleigh.py
gfatpy/atmo/solar.py
gfatpy/cli/main.py
gfatpy/cli/lidar/main.py
gfatpy/cli/lidar/plot/main.py
gfatpy/cloudnet/__init__.py
gfatpy/cloudnet/cloud_model.py
gfatpy/cloudnet/info.yml
gfatpy/cloudnet/plot_deprecated.py
gfatpy/cloudnet/reader.py
gfatpy/cloudnet/utils.py
gfatpy/env_files/info_scc_example.yml
gfatpy/generalife/__init__.py
gfatpy/generalife/_test_generalife.py
gfatpy/generalife/io.py
gfatpy/generalife/licel/LicelReader.py
gfatpy/generalife/licel/LicelUtil.py
gfatpy/generalife/licel/__init__.py
gfatpy/generalife/licel/licel2nc.py
gfatpy/lidar/__init__.py
gfatpy/lidar/info_deprecated.yml
gfatpy/lidar/reader.py
gfatpy/lidar/depolarization/GHK.py
gfatpy/lidar/depolarization/calibration.py
gfatpy/lidar/depolarization/io.py
gfatpy/lidar/depolarization/plot.py
gfatpy/lidar/depolarization/retrieval.py
gfatpy/lidar/depolarization/utils.py
gfatpy/lidar/depolarization/GHK/.hgignore
gfatpy/lidar/depolarization/GHK/.hgtags
gfatpy/lidar/depolarization/GHK/About the effects of polarising optics_4b_1L_corr.pdf
gfatpy/lidar/depolarization/GHK/CHANGELOG.md
gfatpy/lidar/depolarization/GHK/GHK_0.9.8h_Py3.7.py
gfatpy/lidar/depolarization/GHK/Improvements_of_the_GHK_script_200529.pdf
gfatpy/lidar/depolarization/GHK/LICENSE.md
gfatpy/lidar/depolarization/GHK/README.md
gfatpy/lidar/depolarization/GHK/system_settings/__init__.py
gfatpy/lidar/depolarization/GHK/system_settings/mulhacen_polarizer_template.py
gfatpy/lidar/depolarization/GHK/system_settings/mulhacen_rotator_casoG_template.py
gfatpy/lidar/depolarization/GHK/system_settings/mulhacen_run.py
gfatpy-0.16.6.dist-info/METADATA
gfatpy-0.16.6.dist-info/WHEEL
gfatpy-0.16.6.dist-info/entry_points.txt
gfatpy-0.16.6.dist-info/licenses/LICENSE
gfatpy-0.16.6.dist-info/RECORD
