Metadata-Version: 2.4
Name: gfatpy
Version: 0.16.6
Summary: A python package for GFAT utilities
Project-URL: Homepage, https://gfat1.gitlab.io/gfatpy
Author-email: Juan Diego De la Rosa <jdidelarc@gmail.com>
License-Expression: BSD-3-Clause
License-File: LICENSE
Requires-Python: <3.12,>=3.11.11
Requires-Dist: atmospheric-lidar==0.5.4
Requires-Dist: dask<2025,>=2024.11.2
Requires-Dist: importlib
Requires-Dist: ipywidgets<9,>=7.7.1
Requires-Dist: linc==3.0.5
Requires-Dist: loguru<1,>=0.7.0
Requires-Dist: matplotlib>=3.10.0
Requires-Dist: netcdf4<2,>=1.7.2
Requires-Dist: notebook<7,>=6.5.5
Requires-Dist: numba<1,>=0.60.0
Requires-Dist: numpy<2.1,>=2.0.2
Requires-Dist: pandas>=2.1.2
Requires-Dist: pyarrow<19,>=18.1.0
Requires-Dist: pyyaml<7,>=6.0.2
Requires-Dist: requests<3,>=2.32.3
Requires-Dist: rpgpy<0.16,>=0.15.1
Requires-Dist: scipy<2,>=1.13.1
Requires-Dist: seaborn<0.14,>=0.13.2
Requires-Dist: statsmodels<0.15,>=0.14.4
Requires-Dist: typer<1,>=0.15.1
Requires-Dist: typing-extensions<5,>=4.12.0
Requires-Dist: xarray<2026,>=2025.1.2
Provides-Extra: docs
Requires-Dist: pdoc<16,>=15.0.1; extra == 'docs'
Provides-Extra: jupyter
